{
  "m_GameObject": {
    "m_FileID": 0,
    "m_PathID": 0
  },
  "m_Enabled": 1,
  "m_Script": {
    "m_FileID": 0,
    "m_PathID": 8302033850027404168
  },
  "m_Name": "DRamis_SkeletonData",
  "atlasAssets": [
    {
      "m_FileID": 0,
      "m_PathID": 4915344395118012640
    }
  ],
  "scale": 0.01,
  "skeletonJSON": {
    "m_FileID": 0,
    "m_PathID": -2358394819028458291
  },
  "skeletonDataModifiers": [],
  "fromAnimation": [],
  "toAnimation": [],
  "duration": [],
  "defaultMix": 0.2,
  "controller": {
    "m_FileID": 0,
    "m_PathID": 0
  }
}