[
  {
    "id": 1,
    "name": "선인장 판갑\n仙人掌板甲",
    "rarity": "UR",
    "type": "갑옷",
    "faction": "혼돈의 바다",
    "stat_type": "방어력",
    "min_value": 45,
    "max_value": 356,
    "effect": "2비용 이상의 그린 카드를 사용할 때마다 코스트 0.5를 얻는다.",
    "source": "골든원더랜드 - 원더랜드 관리센터"
  },
  {
    "id": 2,
    "name": "자각몽 섬유\n清醒梦纤维",
    "rarity": "UR",
    "type": "갑옷",
    "faction": "철맹",
    "stat_type": "방어력",
    "min_value": 49,
    "max_value": 388,
    "effect": "자신의 레드 카드로 입힌 피해의 2%만큼 자신의 생명력을 회복한다.",
    "source": "철안국 - 임무 수행 훈장 교환"
  },
  {
    "id": 3,
    "name": "공간이동\n错峰出行",
    "rarity": "UR",
    "type": "갑옷",
    "faction": "아니타",
    "stat_type": "방어력",
    "min_value": 49,
    "max_value": 386,
    "effect": "전투 중 적과 아군 모두가 [인뢰]를 발동할 때마다 자신의 생명력을 0.4% 회복한다.",
    "source": "철안국 - 임무 수행 훈장 교환"
  },
  {
    "id": 4,
    "name": "사면직물\n赦免织物",
    "rarity": "UR",
    "type": "갑옷",
    "faction": "학회",
    "stat_type": "방어력",
    "min_value": 47,
    "max_value": 396,
    "effect": "[암흑예술]을 생성할 때, 자신의 방어력이 +2.5% 증가, 최대 65%.",
    "source": "회류탑 - 폰리나 교환"
  },
  {
    "id": 5,
    "name": "자효보갑\n紫宵宝甲",
    "rarity": "UR",
    "type": "갑옷",
    "faction": "흑월",
    "stat_type": "방어력",
    "min_value": 45,
    "max_value": 379,
    "effect": "자신이 [은신] 상태일 때, 자신을 제외한 아군이 받는 피해가 10% 감소한다.",
    "source": "슈그리스 시 - 세실 교환"
  },
  {
    "id": 6,
    "name": "회풍 경연갑\n回风轻烟甲",
    "rarity": "UR",
    "type": "갑옷",
    "faction": "흑월",
    "stat_type": "방어력",
    "min_value": 45,
    "max_value": 379,
    "effect": "아군이 [은신] 상태에 들어갈 때마다 자신의 생명력을 10% 회복한다.",
    "source": "원성대교(远星大桥) - 수리예(苏利耶) - 교환"
  },
  {
    "id": 7,
    "name": "거위 발사기\n鹅制发射器",
    "rarity": "UR",
    "type": "무기",
    "faction": "혼돈의 바다",
    "stat_type": "공격력",
    "min_value": 48,
    "max_value": 381,
    "effect": "[변신]를 일으킬 때마다, 혼란을 유발하는 범위 공격을 가하는 혼돈탄을 발사한다, \n혼돈탄은 폭발물로 취급한다.",
    "source": "골든원더랜드 - 원더랜드 관리센터"
  },
  {
    "id": 8,
    "name": "부러진 검의 불꽃\n断剑之火",
    "rarity": "UR",
    "type": "무기",
    "faction": "학회",
    "stat_type": "공격력",
    "min_value": 48,
    "max_value": 379,
    "effect": "8번의 [점화] 또는 4번의 [작열]을 누적할 때마다 [광염]가 발동된다.",
    "source": "황원역 - 레비스 교환\n(아니타 로켓 발사 센터를 먼저 해제해야 함)"
  },
  {
    "id": 9,
    "name": "축소 폭탄 3호\n缩退炸弹3号",
    "rarity": "UR",
    "type": "무기",
    "faction": "철맹",
    "stat_type": "공격력",
    "min_value": 50,
    "max_value": 392,
    "effect": "33개의 폭발물이 폭발할 때마다 적의 필드에 소형 축소폭탄 3호를 공중 투하하며, \n동시에 [광염]가 발동된다. 폭탄의 위력은 누적된 폭발물의 수에 따라 증가한다. \n축소폭탄 3호는 폭발물로 취급한다.",
    "source": "철맹 전초기지 - 도로시 교환"
  },
  {
    "id": 10,
    "name": "미초용작\n靡草龙雀",
    "rarity": "UR",
    "type": "무기",
    "faction": "흑월",
    "stat_type": "공격력",
    "min_value": 49,
    "max_value": 387,
    "effect": "자신이 [참열]을 일으킬 때마다 공격력이 0.5% 증가하며, 중첩된다.",
    "source": "슈그리스 시 - 세실 교환"
  },
  {
    "id": 11,
    "name": "후회의 갈고리\n悔恨之钩",
    "rarity": "UR",
    "type": "무기",
    "faction": "학회",
    "stat_type": "공격력",
    "min_value": 45,
    "max_value": 358,
    "effect": "[암흑예술]을 사용할 때마다 이번 전투에서 [암흑예술]과 [암흑의 시간]의 피해가 13% 증가한다.\n중첩가능.",
    "source": "골든원더랜드 - 조슈아 교환"
  },
  {
    "id": 12,
    "name": "푸른 환영\n蓝色虚幻",
    "rarity": "UR",
    "type": "무기",
    "faction": "아니타",
    "stat_type": "공격력",
    "min_value": 49,
    "max_value": 387,
    "effect": "방어막을 생성할 때마다 공격력이 0.5% 증가하며, 기존의 방어막 중첩은 제외된다.",
    "source": "아니타 전투 준비 공장 - 일 교환"
  },
  {
    "id": 13,
    "name": "추방 코드\n放逐代码",
    "rarity": "UR",
    "type": "무기",
    "faction": "아니타",
    "stat_type": "공격력",
    "min_value": 47,
    "max_value": 368,
    "effect": "리더스킬 사용 후, 다음 퍼플 카드의 피해가 50% 증가한다.",
    "source": "7호 자유항 도시명성 15레벨 보상"
  },
  {
    "id": 14,
    "name": "외계 성진\n外界星辰",
    "rarity": "UR",
    "type": "무기",
    "faction": "제국",
    "stat_type": "공격력",
    "min_value": 47,
    "max_value": 396,
    "effect": "[신성] / [원소핵] / [초신성]이 생성될 때마다 아군 전체의 공격력이 +1% 증가한다, 최대 20%.",
    "source": "공로성(贡露城) 도시 명성 15레벨 보상"
  },
  {
    "id": 15,
    "name": "보물 탐지기\n探宝枪",
    "rarity": "UR",
    "type": "무기",
    "faction": "혼돈의 바다",
    "stat_type": "공격력",
    "min_value": 46,
    "max_value": 366,
    "effect": "폐기명령으로 카드를 버릴 때, 버린 카드 중 한 장을 손패로 회수한다.",
    "source": "맨더 광산 명성 15레벨 보상"
  },
  {
    "id": 16,
    "name": "이차 상전이\n二级相变",
    "rarity": "UR",
    "type": "무기",
    "faction": "아니타",
    "stat_type": "공격력",
    "min_value": 48,
    "max_value": 380,
    "effect": "자신이 3코스트 이하의 [인뢰] 유발 효과가 있는 카드를 사용할 때마다 [인뢰] 유발 확률이 2% 증가한다\n중첩 가능.",
    "source": "아니타 에너지 연구소 - 관리 센터 교환"
  },
  {
    "id": 17,
    "name": "핵 방사 무기\n核子辐射",
    "rarity": "UR",
    "type": "무기",
    "faction": "철맹",
    "stat_type": "공격력",
    "min_value": 46,
    "max_value": 361,
    "effect": "적을 처치할 때마다 1 코스트를 얻는다.",
    "source": "슈그리스 시 명성 15레벨 보상"
  },
  {
    "id": 18,
    "name": "천룡 람월쇄\n天龙揽月锁",
    "rarity": "UR",
    "type": "무기",
    "faction": "흑월",
    "stat_type": "공격력",
    "min_value": 47,
    "max_value": 391,
    "effect": "비용 2 이상인 족쇄가 포함된 카드를 사용할 때, 랜덤 적 대상의 공격력이 1% 감소, 최대 15%.\n비용 2 이상인 속박이 포함된 카드를 사용할 때, 랜덤 적 대상의 방어력이 1% 감소, 최대 15%.",
    "source": "낙원을 두드리는 문(叩响乐园之门) - 이벤트 상점"
  },
  {
    "id": 19,
    "name": "세계 단결\n世界团结",
    "rarity": "UR",
    "type": "무기",
    "faction": "철맹",
    "stat_type": "공격력",
    "min_value": 47,
    "max_value": 371,
    "effect": "전투 시작 시, 아군 전체가 받는 최종 피해가 30% 감소하며, 20초 동안 지속된다. \n중첩 가능.",
    "source": "철맹 메달 교환"
  },
  {
    "id": 20,
    "name": "공간 접선\n空间切线",
    "rarity": "UR",
    "type": "무기",
    "faction": "아니타",
    "stat_type": "공격력",
    "min_value": 45,
    "max_value": 358,
    "effect": "전투 시작 시, 추가로 카드를 1장 뽑으며, 궁극기 카드를 우선으로 한다.",
    "source": "아니타 로켓 발사 센터 명성 15레벨 보상"
  },
  {
    "id": 21,
    "name": "비뢰파영검\n奔雷破影剑",
    "rarity": "UR",
    "type": "무기",
    "faction": "흑월",
    "stat_type": "공격력",
    "min_value": 47,
    "max_value": 395,
    "effect": "전투 시작 시 또는 카드 덱을 모두 소모하여 셔플이 발생할 때, 카드 1장을 뽑는다. \n이때 레드 카드를 우선적으로 뽑는다.",
    "source": "철산 시 명성 15레벨 보상"
  },
  {
    "id": 22,
    "name": "희생의 곡옥\n身代勾玉",
    "rarity": "UR",
    "type": "펜던트",
    "faction": "흑월",
    "stat_type": "생명력",
    "min_value": 4600,
    "max_value": 38640,
    "effect": "빈사 상태일 때 1초 동안 무적 및 은신 상태가 되며, 동시에 자신의 생명력을 60% 회복한다. \n이 효과는 1회만 발동한다.",
    "source": "람심성(岚心城) 도시 명성 15레벨 보상"
  },
  {
    "id": 23,
    "name": "로고스의 눈\n逻各斯之眼",
    "rarity": "UR",
    "type": "펜던트",
    "faction": "학회",
    "stat_type": "생명력",
    "min_value": 4640,
    "max_value": 36656,
    "effect": "전투 시작 시, 폐기명령을 활성화한다.",
    "source": "황원역 - 레비스 교환\r\n(아니타 로켓 발사 센터를 먼저 해제해야 함)"
  },
  {
    "id": 24,
    "name": "트라페조해드론\n古老偏方三八面体",
    "rarity": "UR",
    "type": "펜던트",
    "faction": "학회",
    "stat_type": "생명력",
    "min_value": 4865,
    "max_value": 38434,
    "effect": "[암흑예술] 사용 시 30% 확률로 비용이 소모되지 않는다.",
    "source": "골든원더랜드 - 조슈아 교환"
  },
  {
    "id": 25,
    "name": "베타 세계선 상자\nβ世界线之盒",
    "rarity": "UR",
    "type": "펜던트",
    "faction": "철맹",
    "stat_type": "생명력",
    "min_value": 4200,
    "max_value": 33180,
    "effect": "적의 한 웨이브를 만날 때마다 카드 한 장을 뽑으며, 자신의 궁극기 카드가 우선된다.",
    "source": "7일 출석 이벤트로 획득"
  },
  {
    "id": 26,
    "name": "헐튼 풍선\n胡尔顿气球",
    "rarity": "UR",
    "type": "펜던트",
    "faction": "혼돈의 바다",
    "stat_type": "생명력",
    "min_value": 4980,
    "max_value": 39342,
    "effect": "3비용 이상의 옐로 카드를 사용할 때마다 카드 한 장을 뽑는다.",
    "source": "철안국 - 임무 수행 훈장 교환"
  },
  {
    "id": 27,
    "name": "달 지는 붉은 구름의 옥새\n月落红云宝玺",
    "rarity": "UR",
    "type": "펜던트",
    "faction": "흑월",
    "stat_type": "생명력",
    "min_value": 4600,
    "max_value": 36340,
    "effect": "손패 최대치가 1장 증가한다.",
    "source": "청명 데이터 센터 명성 15레벨 보상"
  },
  {
    "id": 28,
    "name": "거짓신의 속삭임\n伪神低语",
    "rarity": "UR",
    "type": "펜던트",
    "faction": "아니타",
    "stat_type": "생명력",
    "min_value": 4790,
    "max_value": 37841,
    "effect": "아군 전체 드론의 지속 시간이 1초 연장된다.\n중첩 가능.",
    "source": "아니타 로켓 발사 센터 - 칼레아 교환"
  },
  {
    "id": 29,
    "name": "100만 초자기체\n百万超磁体",
    "rarity": "UR",
    "type": "펜던트",
    "faction": "철맹",
    "stat_type": "생명력",
    "min_value": 4855,
    "max_value": 40782,
    "effect": "비용이 3 이상인 레드 카드/블루 카드를 사용할 때, 카드 덱에서 레드 카드/블루 카드 2장을 손패에 추가한다. \n단, 이 효과는 1회만 발동한다.",
    "source": "운수교 기지 - 소맥 교환"
  },
  {
    "id": 30,
    "name": "113호 압수 물품\n113号没收物品",
    "rarity": "UR",
    "type": "펜던트",
    "faction": "혼돈의 바다",
    "stat_type": "생명력",
    "min_value": 4855,
    "max_value": 40782,
    "effect": "자신의 비용 5 이상인 스킬 카드의 소모 비용이 -1 감소한다.",
    "source": "운수교 기지 - 교화센터 교환상점"
  },
  {
    "id": 31,
    "name": "팔방 복룡진\n八方伏龙阵",
    "rarity": "UR",
    "type": "펜던트",
    "faction": "흑월",
    "stat_type": "생명력",
    "min_value": 4640,
    "max_value": 38976,
    "effect": "카드 8장을 뽑을 때마다 코스트 0.8을 회복한다.",
    "source": "청명 이문 기담 - 이벤트 상점"
  },
  {
    "id": 32,
    "name": "찬란한 성석\n璀璨星石",
    "rarity": "UR",
    "type": "펜던트",
    "faction": "학회",
    "stat_type": "생명력",
    "min_value": 4695,
    "max_value": 39439,
    "effect": "카드 덱에서 블랙카드,음의에너지를 뽑을 경우, 해당 카드를 소멸시키고 대신 [신성]을 손패에 생성한다.",
    "source": "회류탑 - 폰리나 - 교환"
  },
  {
    "id": 33,
    "name": "초인과의 주사위\n超因果之骰",
    "rarity": "UR",
    "type": "펜던트",
    "faction": "학회",
    "stat_type": "생명력",
    "min_value": 4585,
    "max_value": 38515,
    "effect": "아군의 모든 확률 메커니즘발동 확률 +3%\n중첩 가능",
    "source": "해각시 명성 15레벨 보상"
  },
  {
    "id": 34,
    "name": "헤븐 아머\n天王宝铠",
    "rarity": "SSR",
    "type": "갑옷",
    "faction": "흑월",
    "stat_type": "방어력",
    "min_value": 37,
    "max_value": 295,
    "effect": "자신의 스킬 카드를 사용할 때 2초간 [슈퍼 아머] 상태가된다.\n중첩 가능",
    "source": "곤루시 - 철안국 현상수배 임무\n흑월 상점\n운행 노선 자작나무 부표 드랍"
  },
  {
    "id": 35,
    "name": "정원 수호\n花园守护",
    "rarity": "SSR",
    "type": "갑옷",
    "faction": "제국",
    "stat_type": "방어력",
    "min_value": 37,
    "max_value": 294,
    "effect": "매 초 자신의 생명력이 0.5% 회복된다",
    "source": "흑월 상점\r\n운행 노선 자작나무 부표 드랍"
  },
  {
    "id": 36,
    "name": "흑석 아머\n黑石护甲",
    "rarity": "SSR",
    "type": "갑옷",
    "faction": "철맹",
    "stat_type": "방어력",
    "min_value": 37,
    "max_value": 295,
    "effect": "받는 최종 피해가 10% 감소한다.\r\n중첩 가능",
    "source": "슈그리 시 - 철도 보안국 현상금 임무\n멘더 광산 -  철 안전국 현상금 임무\n황원역 - 전투 계획\n흑월 상점\n운행 노선 자작나무 부표 드랍"
  },
  {
    "id": 37,
    "name": "고차원 구조체\n高维构造体",
    "rarity": "SSR",
    "type": "갑옷",
    "faction": "학회",
    "stat_type": "방어력",
    "min_value": 38,
    "max_value": 297,
    "effect": "블랙 카드를 생성할 때, 자신의 생명력이 5% 회복된다.\n중첩 가능",
    "source": "해각시 - 철안국 현상금 임무\n흑월 상점\n황원역 - 레비스 교환\n운행 노선 자작나무 부표 드랍"
  },
  {
    "id": 38,
    "name": "시뮬레이트 스타\n模拟星辰",
    "rarity": "SSR",
    "type": "갑옷",
    "faction": "아니타",
    "stat_type": "방어력",
    "min_value": 37,
    "max_value": 289,
    "effect": "리더스킬 사용 시, 자신의 생명력이 5% 회복된다.\r\n중첩 가능",
    "source": "7호 자유항 - 철도보안국 현상금 임무\r\n에너지 연구소  - 작전 계획\r\n흑월 상점\r\n운행 노선 자작나무 부표 드랍"
  },
  {
    "id": 39,
    "name": "낙뢰의 심면나무 갑옷\n雷击深眠木甲",
    "rarity": "SSR",
    "type": "갑옷",
    "faction": "혼돈의 바다",
    "stat_type": "방어력",
    "min_value": 37,
    "max_value": 314,
    "effect": "자신이 받는 [참열] 및 [열상] 피해가 50% 감소한다.\n피해를 준 대상에게 15% 확률로 낙뢰를 발동한다.",
    "source": "낙원을 두드리는 문(叩响乐园之门) - 이벤트 상점"
  },
  {
    "id": 40,
    "name": "무한 비확률 아머\n无限非概率护甲",
    "rarity": "SSR",
    "type": "갑옷",
    "faction": "학회",
    "stat_type": "방어력",
    "min_value": 39,
    "max_value": 330,
    "effect": "캐릭터가 한 번에 최대 생명력의 33%를 초과하는 피해를 받을 경우, \n해당 피해를 면역한다. 이 효과는 1회만 발동한다.",
    "source": "회류탑 - 폰 리나 교환"
  },
  {
    "id": 41,
    "name": "메모리 청심\n内存清心咒",
    "rarity": "SSR",
    "type": "갑옷",
    "faction": "흑월",
    "stat_type": "방어력",
    "min_value": 39,
    "max_value": 331,
    "effect": "자신의 스킬 카드 덱에 블루 카드가 없을 경우, 받는 최종 피해가 15% 감소한다.",
    "source": "흑월 계열 장비 상자"
  },
  {
    "id": 42,
    "name": "메모리 매트릭스\n外部记忆矩阵",
    "rarity": "SSR",
    "type": "갑옷",
    "faction": "학회",
    "stat_type": "방어력",
    "min_value": 37,
    "max_value": 312,
    "effect": "받는 피해가 최대 33%를 넘지 않는다.",
    "source": "운행 노선 자작나무 부표 드랍\n원성대교(远星大桥) 건설 진행도 보상\n학회 관련 장비상자"
  },
  {
    "id": 43,
    "name": "치유 방탄 조끼\n治愈防弹衣",
    "rarity": "SSR",
    "type": "갑옷",
    "faction": "철맹",
    "stat_type": "방어력",
    "min_value": 38,
    "max_value": 317,
    "effect": "그린 카드를 사용할 때마다 자신의 생명력을 5% 회복한다.",
    "source": "운행 노선 자작나무 부표 드랍\n철맹 관련 장비상자"
  },
  {
    "id": 44,
    "name": "본드래곤 갑옷\n骨龙护甲",
    "rarity": "SSR",
    "type": "갑옷",
    "faction": "혼돈의 바다",
    "stat_type": "방어력",
    "min_value": 40,
    "max_value": 334,
    "effect": "자신이 받는 얼음 피해가 15% 감소하며, 30% 확률로 [냉동] 효과를 무효로한다.",
    "source": "운행 노선 자작나무 부표 드랍\n혼돈의 바다 귀중 장비 상자"
  },
  {
    "id": 45,
    "name": "진홍의 예언\n深红谶言",
    "rarity": "SSR",
    "type": "갑옷",
    "faction": "학회",
    "stat_type": "방어력",
    "min_value": 39,
    "max_value": 325,
    "effect": "[부식] 또는 [잠식]로 입힌 피해의 5%만큼 자신의 생명력을 회복한다.",
    "source": "운행 노선 자작나무 부표 드랍\n학회 관련 장비상자"
  },
  {
    "id": 46,
    "name": "데몬베인의 갑옷\n机神甲胄",
    "rarity": "SSR",
    "type": "갑옷",
    "faction": "흑월",
    "stat_type": "방어력",
    "min_value": 40,
    "max_value": 3000,
    "effect": "[참열] 또는 [열상]으로 입힌 피해의 5%만큼 자신의 생명력을 회복한다.",
    "source": "운행 노선 자작나무 부표 드랍\n흑월 관련 장비상자"
  },
  {
    "id": 47,
    "name": "반란자의 이마보호대\n黑月叛忍护额",
    "rarity": "SSR",
    "type": "갑옷",
    "faction": "흑월",
    "stat_type": "방어력",
    "min_value": 39,
    "max_value": 331,
    "effect": "받는 물리 피해가 15% 감소하고 동시에 30% 확률로 [붕괴] 효과에 면역이 된다.",
    "source": "운행 노선 자작나무 부표 드랍\n흑월 관련 장비상자"
  },
  {
    "id": 48,
    "name": "아구나토\n阿古纳托",
    "rarity": "SSR",
    "type": "무기",
    "faction": "혼돈의 바다",
    "stat_type": "공격력",
    "min_value": 40,
    "max_value": 318,
    "effect": "자신이 일으킨 [붕괴] 지속 시간이 2초 연장된다.\n중첩 가능.",
    "source": "골든원더랜드 - 작전 계획\n흑월 상점\n운행 노선 자작나무 부표 드랍"
  },
  {
    "id": 49,
    "name": "별의 자취\n暗夜寻星",
    "rarity": "SSR",
    "type": "무기",
    "faction": "제국",
    "stat_type": "공격력",
    "min_value": 38,
    "max_value": 301,
    "effect": "퍼플카드를 사용할 때, 10% 확률로 [신성] 카드 한 장을 손패에 추가한다. \n확률 중첩 가능.",
    "source": "흑월 상점\n운행 노선 자작나무 부표 드랍"
  },
  {
    "id": 50,
    "name": "라이트 체이서\n光芒追击者",
    "rarity": "SSR",
    "type": "무기",
    "faction": "제국",
    "stat_type": "공격력",
    "min_value": 37,
    "max_value": 293,
    "effect": "[이상한 불꽃]이 일으키는 피해가 20% 증가한다.\n 중첩 가능.",
    "source": "흑월 상점\r\n운행 노선 자작나무 부표 드랍"
  },
  {
    "id": 51,
    "name": "엠비션\n野心",
    "rarity": "SSR",
    "type": "무기",
    "faction": "제국",
    "stat_type": "공격력",
    "min_value": 40,
    "max_value": 316,
    "effect": "자신이 일으키는 [참열] 피해가 25% 증가한다. \n중첩 가능.",
    "source": "흑월 상점\n운행 노선 자작나무 부표 드랍"
  },
  {
    "id": 52,
    "name": "측퇴 흑석\n简并黑石",
    "rarity": "SSR",
    "type": "무기",
    "faction": "철맹",
    "stat_type": "공격력",
    "min_value": 38,
    "max_value": 301,
    "effect": "최종 피해량이 10% 증가한다. \n중첩 가능.",
    "source": "슈그리 시 - 철도 보안국 현상금 임무\n멘더 광산 -  철 안전국 현상금 임무\n황원역 - 전투 계획\n흑월 상점\n운행 노선 자작나무 부표 드랍"
  },
  {
    "id": 53,
    "name": "비트레이얼\n狡诈背叛",
    "rarity": "SSR",
    "type": "무기",
    "faction": "학회",
    "stat_type": "공격력",
    "min_value": 37,
    "max_value": 294,
    "effect": "리더스킬 사용 시, 20% 확률로 [암흑예술] 카드 한 장이 덱 최상단에 추가된다.\n확률 중첩 가능",
    "source": "해각시 - 철안국 현상금 임무\n흑월 상점\n운행 노선 자작나무 부표 드랍"
  },
  {
    "id": 54,
    "name": "인비져블 터치\n不可见之触",
    "rarity": "SSR",
    "type": "무기",
    "faction": "학회",
    "stat_type": "공격력",
    "min_value": 40,
    "max_value": 313,
    "effect": "[암흑예술]이 일으키는 피해가 20% 증가한다. \n중첩 가능",
    "source": "해각시 - 철안국 현상금 임무\r\n흑월 상점\r\n운행 노선 자작나무 부표 드랍"
  },
  {
    "id": 55,
    "name": "볼케이노\n火山",
    "rarity": "SSR",
    "type": "무기",
    "faction": "제국",
    "stat_type": "공격력",
    "min_value": 40,
    "max_value": 313,
    "effect": "자신이 일으키는 [점화], [작열], [광염], [불바다]의 초당 연소 피해가 25% 증가한다.\n중첩 가능",
    "source": "흑월 상점\r\n운행 노선 자작나무 부표 드랍"
  },
  {
    "id": 56,
    "name": "노던 프릭클\n北方荆棘",
    "rarity": "SSR",
    "type": "무기",
    "faction": "혼돈의 바다",
    "stat_type": "공격력",
    "min_value": 40,
    "max_value": 313,
    "effect": "자신이 일으키는 [족쇄]와 [속박] 지속 시간이 2초 연장된다.\n중첩 가능",
    "source": "골든원더랜드 - 작전 계획\n흑월 상점\n운행 노선 자작나무 부표 드랍"
  },
  {
    "id": 57,
    "name": "라바 파이어\n活火熔岩",
    "rarity": "SSR",
    "type": "무기",
    "faction": "아니타",
    "stat_type": "공격력",
    "min_value": 38,
    "max_value": 298,
    "effect": "자신이 일으키는 [점화], [작열], [광염] 지속 시간이 2초 연장된다.\n중첩 가능",
    "source": "7호 자유항 - 철도보안국 현상금 임무\n에너지 연구소  - 작전 계획\n흑월 상점\n운행 노선 자작나무 부표 드랍"
  },
  {
    "id": 58,
    "name": "흑월 메테오\n雾夜流星",
    "rarity": "SSR",
    "type": "무기",
    "faction": "흑월",
    "stat_type": "공격력",
    "min_value": 39,
    "max_value": 308,
    "effect": "자신의 [은신] 지속 시간이 2초 연장된다.\n중첩 가능",
    "source": "곤루시 - 철안국 현상수배 임무\n흑월 상점\r\n운행 노선 자작나무 부표 드랍"
  },
  {
    "id": 59,
    "name": "스피릿 보우\n灵狐名弓",
    "rarity": "SSR",
    "type": "무기",
    "faction": "흑월",
    "stat_type": "공격력",
    "min_value": 39,
    "max_value": 310,
    "effect": "자신이 일으킨 [발사] 횟수 +1",
    "source": "곤루시 - 철안국 현상수배 임무\n흑월 상점\n운행 노선 자작나무 부표 드랍"
  },
  {
    "id": 60,
    "name": "반엔트로피\n逆熵严冬",
    "rarity": "SSR",
    "type": "무기",
    "faction": "아니타",
    "stat_type": "공격력",
    "min_value": 40,
    "max_value": 316,
    "effect": "자신이 일으키는 [냉동] 및 [동결] 지속시간이 2초 연장된다.\n중첩가능",
    "source": "7호 자유항 - 철도보안국 현상금 임무\n에너지 연구소  - 작전 계획\n흑월 상점\n운행 노선 자작나무 부표 드랍"
  },
  {
    "id": 61,
    "name": "불꽃 침식자\n炽焰侵蚀者",
    "rarity": "SSR",
    "type": "무기",
    "faction": "제국",
    "stat_type": "공격력",
    "min_value": 37,
    "max_value": 289,
    "effect": "일반 공격 시 15% 확률로 [점화]를 발동한다.",
    "source": "흑월 상점\r\n운행 노선 자작나무 부표 드랍"
  },
  {
    "id": 62,
    "name": "세븐 스트링 보우\n七弦弓",
    "rarity": "SSR",
    "type": "무기",
    "faction": "제국",
    "stat_type": "공격력",
    "min_value": 39,
    "max_value": 308,
    "effect": "자신이 일으키는 [저주]의 지속 시간이 2초 연장된다. \n중첩 가능",
    "source": "흑월 상점\n운행 노선 자작나무 부표 드랍"
  },
  {
    "id": 63,
    "name": "타임라인 익스텐더\n时间延展线",
    "rarity": "SSR",
    "type": "무기",
    "faction": "철맹",
    "stat_type": "공격력",
    "min_value": 37,
    "max_value": 295,
    "effect": "자신의 [일반 공격] 속도가 25% 증가한다.\r\n중첩 가능",
    "source": "슈그리 시 - 철도 보안국 현상금 임무\n멘더 광산 -  철 안전국 현상금 임무\n황원역 - 전투 계획\n흑월 상점\n운행 노선 자작나무 부표 드랍"
  },
  {
    "id": 64,
    "name": "토르\n雷神",
    "rarity": "SSR",
    "type": "무기",
    "faction": "제국",
    "stat_type": "공격력",
    "min_value": 39,
    "max_value": 306,
    "effect": "자신이 일으키는 [인뢰], [낙뢰], [우레] 및 [천둥]의 피해가 25% 증가한다.\n중첩 가능",
    "source": "흑월 상점\n운행 노선 자작나무 부표 드랍"
  },
  {
    "id": 65,
    "name": "낙뢰의 심면나무 검\n雷击深眠木剑",
    "rarity": "SSR",
    "type": "무기",
    "faction": "혼돈의 바다",
    "stat_type": "공격력",
    "min_value": 40,
    "max_value": 338,
    "effect": "자신이 [참열]을 발생시킬 때, 동시에 [인뢰]를 발동한다.",
    "source": "낙원을 두드리는 문(叩响乐园之门) - 이벤트 상점"
  },
  {
    "id": 66,
    "name": "반항의 벌칙\n抗拒从严",
    "rarity": "SSR",
    "type": "무기",
    "faction": "혼돈의 바다",
    "stat_type": "공격력",
    "min_value": 37,
    "max_value": 309,
    "effect": "자신이 가하는 화염 피해가 15% 증가한다.",
    "source": "운수교 교화센터 - 교환 상점"
  },
  {
    "id": 67,
    "name": "불법 공예품\n违禁工艺品",
    "rarity": "SSR",
    "type": "무기",
    "faction": "혼돈의 바다",
    "stat_type": "공격력",
    "min_value": 38,
    "max_value": 322,
    "effect": "자신의 일반 공격 피해가 25% 증가한다.",
    "source": "운행 노선 자작나무 부표 드랍\n\n운수교 기지 건설 진행도 보상"
  },
  {
    "id": 68,
    "name": "심해 시험침\n深海探针",
    "rarity": "SSR",
    "type": "무기",
    "faction": "학회",
    "stat_type": "공격력",
    "min_value": 39,
    "max_value": 331,
    "effect": "비용 3 이상인 레드 카드를 사용할 때, 랜덤 적 대상의 치유 효과가 3% 감소한다. \n최대 75%, 중첩 가능.",
    "source": "운행 노선 자작나무 부표 드랍\n\n회류탑 건설 진행도 보상"
  },
  {
    "id": 69,
    "name": "스타 웨이브\n星弧波纹",
    "rarity": "SSR",
    "type": "무기",
    "faction": "학회",
    "stat_type": "공격력",
    "min_value": 40,
    "max_value": 334,
    "effect": "리더 스킬을 사용할 때, 펄스를 방출하여 적 전체가 받는 혼향 피해를 1% 증가시킨다. \n최대 5%, 중첩 가능.",
    "source": "회류탑 - 폰 리나 교환\n\n운행 노선 자작나무 부표 드랍"
  },
  {
    "id": 70,
    "name": "오니란 스태프\n奥尼兰法杖",
    "rarity": "SSR",
    "type": "무기",
    "faction": "제국",
    "stat_type": "공격력",
    "min_value": 38,
    "max_value": 317,
    "effect": "자신이 가하는 잔향 피해가 15% 증가한다.",
    "source": "운행 노선 자작나무 부표 드랍\n\n제국 관련 장비상자"
  },
  {
    "id": 71,
    "name": "북두항마검\n天罡伏魔剑",
    "rarity": "SSR",
    "type": "무기",
    "faction": "흑월",
    "stat_type": "공격력",
    "min_value": 37,
    "max_value": 309,
    "effect": "자신이 가하는 물리 피해가 15% 증가한다.",
    "source": "운행 노선 자작나무 부표 드랍\n\n흑월 관련 장비상자"
  },
  {
    "id": 72,
    "name": "액체 질소 분사기\n液氮喷射器",
    "rarity": "SSR",
    "type": "무기",
    "faction": "철맹",
    "stat_type": "공격력",
    "min_value": 39,
    "max_value": 326,
    "effect": "자신이 가하는 얼음 피해가 15% 증가한다.",
    "source": "운행 노선 자작나무 부표 드랍\n\n철맹 관련 장비상자"
  },
  {
    "id": 73,
    "name": "넥타르의 마지막 해\n尼克塔尔最后解",
    "rarity": "SSR",
    "type": "무기",
    "faction": "학회",
    "stat_type": "공격력",
    "min_value": 39,
    "max_value": 326,
    "effect": "자신이 가하는 부정 에너지 피해가 15% 증가한다.",
    "source": "운행 노선 자작나무 부표 드랍\n\n학회 관련 장비상자"
  },
  {
    "id": 74,
    "name": "구상번개\n球状闪电",
    "rarity": "SSR",
    "type": "무기",
    "faction": "아니타",
    "stat_type": "공격력",
    "min_value": 39,
    "max_value": 328,
    "effect": "자신의 스킬 카드를 사용할 때, 적을 관통하는 작은 구형 번개를 방출한다. \n번개는 적중 시 1단 피해를 입히며, 동시에 [인뢰]를 발동한다.",
    "source": "운행 노선 자작나무 부표 드랍\n\n아니타 관련 장비상자"
  },
  {
    "id": 75,
    "name": "번개 에너지 부적\n五雷供电符",
    "rarity": "SSR",
    "type": "무기",
    "faction": "흑월",
    "stat_type": "공격력",
    "min_value": 40,
    "max_value": 336,
    "effect": "전투 시작 시 랜덤으로 손패에서 카드 1장을 버린다. \n이후 아군 전체가 가하는 전자기 피해가 10% 증가한다. \n중첩 가능",
    "source": "청명 이문 기담(澄明异闻奇谈) - 이벤트 상점"
  },
  {
    "id": 76,
    "name": "모노폴 마그네타\n单极磁星",
    "rarity": "SSR",
    "type": "펜던트",
    "faction": "아니타",
    "stat_type": "생명력",
    "min_value": 3791,
    "max_value": 29948,
    "effect": "자신의 드론 지속 시간이 2초 연장된다.\n중첩 가능",
    "source": "7호 자유항 - 철도보안국 현상금 임무\n에너지 연구소  - 작전 계획\n흑월 상점\n운행 노선 자작나무 부표 드랍"
  },
  {
    "id": 77,
    "name": "춘추합성인장\n春秋合诚印",
    "rarity": "SSR",
    "type": "펜던트",
    "faction": "흑월",
    "stat_type": "생명력",
    "min_value": 3734,
    "max_value": 29499,
    "effect": "시작시 2코스트가 추가로 주어진다.\n중첩 가능",
    "source": "곤루시 - 철안국 현상수배 임무\n흑월 상점\n운행 노선 자작나무 부표 드랍"
  },
  {
    "id": 78,
    "name": "변화의 눈동자\n万变眼眸",
    "rarity": "SSR",
    "type": "펜던트",
    "faction": "학회",
    "stat_type": "생명력",
    "min_value": 3754,
    "max_value": 29659,
    "effect": "[암흑예술]을 생성할 때, 자신의 생명력이 5% 회복된다.\n중첩 가능",
    "source": "해각시 - 철안국 현상금 임무\n흑월 상점\n황원역 - 레비스 교환\n운행 노선 자작나무 부표 드랍"
  },
  {
    "id": 79,
    "name": "리프팅 수술 장비\n升构手术器",
    "rarity": "SSR",
    "type": "펜던트",
    "faction": "철맹",
    "stat_type": "생명력",
    "min_value": 3815,
    "max_value": 30139,
    "effect": "적의 한 웨이브를 처치할때 마다, 아군 전체의 생명력이 8% 회복된다.\n중첩 가능",
    "source": "슈그리 시 - 철도 보안국 현상금 임무\r\n멘더 광산 -  철 안전국 현상금 임무\r\n황원역 - 전투 계획\r\n흑월 상점\r\n운행 노선 자작나무 부표 드랍"
  },
  {
    "id": 80,
    "name": "최면의 시계\n催眠怀表",
    "rarity": "SSR",
    "type": "펜던트",
    "faction": "혼돈의 바다",
    "stat_type": "생명력",
    "min_value": 3888,
    "max_value": 30715,
    "effect": "자신이 일으키는 [수면]의 지속 시간이 2초 연장된다.\n중첩 가능",
    "source": "골든원더랜드 - 작전 계획\n흑월 상점\n운행 노선 자작나무 부표 드랍"
  },
  {
    "id": 81,
    "name": "성핵 잔화\n星核余烬",
    "rarity": "SSR",
    "type": "펜던트",
    "faction": "제국",
    "stat_type": "생명력",
    "min_value": 4014,
    "max_value": 31707,
    "effect": "[신성], [원소핵] 및 [초신성]이 일으키는 피해가 20% 증가한다.\n중첩 가능",
    "source": "흑월 상점\n운행 노선 자작나무 부표 드랍"
  },
  {
    "id": 82,
    "name": "뫼비우스\n莫比乌斯",
    "rarity": "SSR",
    "type": "펜던트",
    "faction": "아니타",
    "stat_type": "생명력",
    "min_value": 4026,
    "max_value": 31803,
    "effect": "손패 보충 쿨타임이 0.25초 단축된다. \n중첩가능.",
    "source": "7호 자유항 - 철도보안국 현상금 임무\n에너지 연구소  - 작전 계획\n흑월 상점\n운행 노선 자작나무 부표 드랍"
  },
  {
    "id": 83,
    "name": "낙뢰의 심면나무 부적\n雷击深眠木护符",
    "rarity": "SSR",
    "type": "펜던트",
    "faction": "혼돈의 바다",
    "stat_type": "생명력",
    "min_value": 3888,
    "max_value": 32659,
    "effect": "매 6초마다 1회 발동하며, 피해를 받을 때 자신이 받는 피해가 40% 감소한다. \n지속 시간 2초.",
    "source": "낙원을 두드리는 문(叩响乐园之门) - 이벤트 상점"
  },
  {
    "id": 84,
    "name": "전술 풍수 드론\n战术风水无人机",
    "rarity": "SSR",
    "type": "펜던트",
    "faction": "흑월",
    "stat_type": "생명력",
    "min_value": 3840,
    "max_value": 32252,
    "effect": "카드 8장을 사용할 때마다 자신의 공격력 또는 방어력이 2% 증가한다.\n최대 50%",
    "source": "청명 이문 기담(澄明异闻奇谈) - 이벤트 상점"
  },
  {
    "id": 85,
    "name": "클라드니 아크\n克拉尼弧光",
    "rarity": "SSR",
    "type": "펜던트",
    "faction": "학회",
    "stat_type": "생명력",
    "min_value": 3993,
    "max_value": 33543,
    "effect": "자신의 파동이 가하는 피해가 20% 증가\n중첩가능",
    "source": "운행 노선 자작나무 부표 드랍\n학회 관련 장비 상자"
  },
  {
    "id": 86,
    "name": "봉인된 사중 재난\n被封印的四重灾厄",
    "rarity": "SSR",
    "type": "펜던트",
    "faction": "제국",
    "stat_type": "생명력",
    "min_value": 4014,
    "max_value": 33714,
    "effect": "[소환수] 속성이 있는 카드를 사용할 때마다 자신의 생명력을 3% 회복한다.\n또한 전장에 있는 [소환수]마다 추가로 자신의 생명력을 2% 회복한다.\n중첩 가능",
    "source": "운행 노선 자작나무 부표 드랍\n제국 관련 장비 상자"
  },
  {
    "id": 87,
    "name": "이계의 별빛\n异界星光",
    "rarity": "SR",
    "type": "갑옷",
    "faction": "제국",
    "stat_type": "방어력",
    "min_value": 29,
    "max_value": 230,
    "effect": "[이상한 불꽃]이 일으키는 피해의 5%만큼 자신의 생명력 회복한다.\n중첩 가능",
    "source": "흑월 상점\n운행 노선 자작나무 부표 드랍"
  },
  {
    "id": 88,
    "name": "열광학 위장 장치\n热光学迷彩",
    "rarity": "SR",
    "type": "갑옷",
    "faction": "흑월",
    "stat_type": "방어력",
    "min_value": 30,
    "max_value": 237,
    "effect": "자신의 생명력이 30% 이하일 때, 5초간 은신상태가된다.\n1회 한정",
    "source": "곤루시 - 철안국 현상수배 임무\n흑월 상점\n운행 노선 자작나무 부표 드랍"
  },
  {
    "id": 89,
    "name": "블락 금속\n御险金属",
    "rarity": "SR",
    "type": "갑옷",
    "faction": "학회",
    "stat_type": "방어력",
    "min_value": 31,
    "max_value": 243,
    "effect": "폐기명령 사용 시, 자신의 생명력을 10% 회복한다.\n중첩 가능",
    "source": "해각시 - 철안국 현상금 임무\n흑월 상점\n황원역 - 레비스 교환\n운행 노선 자작나무 부표 드랍"
  },
  {
    "id": 90,
    "name": "공명체 섬유\n共振体纤维",
    "rarity": "SR",
    "type": "갑옷",
    "faction": "아니타",
    "stat_type": "방어력",
    "min_value": 29,
    "max_value": 229,
    "effect": "자신의 스킬 카드를 사용할 때, 자신의 생명력 2%를 회복한다.",
    "source": "7호 자유항 - 철도보안국 현상금 임무\n에너지 연구소  - 작전 계획\n흑월 상점\n운행 노선 자작나무 부표 드랍"
  },
  {
    "id": 91,
    "name": "북부동맹 방어 섬유\n北阵防御纤维",
    "rarity": "SR",
    "type": "갑옷",
    "faction": "철맹",
    "stat_type": "방어력",
    "min_value": 30,
    "max_value": 236,
    "effect": "적을 처치할 때마다, 자신의 생명력 5%를 회복한다.\n중첩 가능",
    "source": "슈그리 시 - 철도 보안국 현상금 임무\n멘더 광산 -  철 안전국 현상금 임무\n황원역 - 전투 계획\n흑월 상점\n운행 노선 자작나무 부표 드랍"
  },
  {
    "id": 92,
    "name": "범죄의 증거\n“罪证”",
    "rarity": "SR",
    "type": "무기",
    "faction": "흑월",
    "stat_type": "공격력",
    "min_value": 30,
    "max_value": 235,
    "effect": "자신이 일으키는 중상 지속 시간이 2초 연장된다.\n중첩 가능",
    "source": "곤루시 - 철안국 현상수배 임무\n흑월 상점\n운행 노선 자작나무 부표 드랍"
  },
  {
    "id": 93,
    "name": "광명의 염원\n光明之愿",
    "rarity": "SR",
    "type": "무기",
    "faction": "제국",
    "stat_type": "공격력",
    "min_value": 30,
    "max_value": 238,
    "effect": "[신성]을 사용할 때, 중단 효과 발동",
    "source": "흑월 상점\r\n운행 노선 자작나무 부표 드랍"
  },
  {
    "id": 94,
    "name": "동력식 도끼\n动力伐木斧",
    "rarity": "SR",
    "type": "무기",
    "faction": "철맹",
    "stat_type": "공격력",
    "min_value": 32,
    "max_value": 250,
    "effect": "적을 처치할 때마다, 자신의 방어력이 1% 증가한다.\n중첩 가능",
    "source": "슈그리 시 - 철도 보안국 현상금 임무\n멘더 광산 -  철 안전국 현상금 임무\n황원역 - 전투 계획\n흑월 상점\n운행 노선 자작나무 부표 드랍"
  },
  {
    "id": 95,
    "name": "에비서레이터MK0\n内脏采集器MK0",
    "rarity": "SR",
    "type": "무기",
    "faction": "아니타",
    "stat_type": "공격력",
    "min_value": 30,
    "max_value": 236,
    "effect": "리더스킬 사용 시, 0.4 코스트 비용을 획득한다.\n중첩 가능",
    "source": "7호 자유항 - 철도보안국 현상금 임무\n에너지 연구소  - 작전 계획\n흑월 상점\n운행 노선 자작나무 부표 드랍"
  },
  {
    "id": 96,
    "name": "라이플총\n老兵步枪",
    "rarity": "SR",
    "type": "무기",
    "faction": "철맹",
    "stat_type": "공격력",
    "min_value": 30,
    "max_value": 236,
    "effect": "적을 처치할 때마다, 자신의 공격력이 1% 증가한다.\n중첩 가능",
    "source": "슈그리 시 - 철도 보안국 현상금 임무\r\n멘더 광산 -  철 안전국 현상금 임무\r\n황원역 - 전투 계획\r\n흑월 상점\r\n운행 노선 자작나무 부표 드랍"
  },
  {
    "id": 97,
    "name": "\"청산\"\n“清算”",
    "rarity": "SR",
    "type": "무기",
    "faction": "흑월",
    "stat_type": "공격력",
    "min_value": 29,
    "max_value": 228,
    "effect": "자신이 일으키는 열상의 지속 시간이 2초 연장된다.\n중첩 가능",
    "source": "곤루시 - 철안국 현상수배 임무\n흑월 상점\n운행 노선 자작나무 부표 드랍"
  },
  {
    "id": 98,
    "name": "해부 도구 C\n解剖工具C",
    "rarity": "SR",
    "type": "무기",
    "faction": "학회",
    "stat_type": "공격력",
    "min_value": 29,
    "max_value": 228,
    "effect": "폐기 명령 사용 시, 1 코스트 비용 획득.\n중첩 가능",
    "source": "해각시 - 철안국 현상금 임무\n흑월 상점\n황원역 - 레비스 교환\n운행 노선 자작나무 부표 드랍"
  },
  {
    "id": 99,
    "name": "임계 질량\n临界质量",
    "rarity": "SR",
    "type": "무기",
    "faction": "학회",
    "stat_type": "공격력",
    "min_value": 29,
    "max_value": 230,
    "effect": "자신이 일으키는 기절 지속 시간이 1초 연장된다.\n중첩 가능",
    "source": "해각시 - 철안국 현상금 임무\n흑월 상점\n운행 노선 자작나무 부표 드랍"
  },
  {
    "id": 100,
    "name": "번개 소환 권선기 MK1\n唤雷线圈MK1",
    "rarity": "SR",
    "type": "무기",
    "faction": "아니타",
    "stat_type": "공격력",
    "min_value": 30,
    "max_value": 237,
    "effect": "자신이 [인뢰]를 일으킬 확률이 8% 증가한다.\n중첩 가능",
    "source": "7호 자유항 - 철도보안국 현상금 임무\n에너지 연구소  - 작전 계획\n흑월 상점\n운행 노선 자작나무 부표 드랍"
  },
  {
    "id": 101,
    "name": "야밤의 별\n良夜远星",
    "rarity": "SR",
    "type": "무기",
    "faction": "제국",
    "stat_type": "공격력",
    "min_value": 31,
    "max_value": 246,
    "effect": "퍼플 카드를 사용한 후, 자신의 생명력이 2% 회복된다.",
    "source": "흑월 상점\n운행 노선 자작나무 부표 드랍"
  },
  {
    "id": 102,
    "name": "보라빛 써스데이\n紫色星期四",
    "rarity": "SR",
    "type": "무기",
    "faction": "혼돈의 바다",
    "stat_type": "공격력",
    "min_value": 30,
    "max_value": 239,
    "effect": "자신의 [광포] 지속 시간이 2초 연장된다. 중첩 가능\n동시에 [수면] 효과의 지속 시간이 2초 감소한다. 중첩 가능",
    "source": "골든원더랜드 - 작전 계획\n흑월 상점\n운행 노선 자작나무 부표 드랍"
  },
  {
    "id": 103,
    "name": "블락 플래셔\n御敌闪光器",
    "rarity": "SR",
    "type": "무기",
    "faction": "학회",
    "stat_type": "공격력",
    "min_value": 29,
    "max_value": 229,
    "effect": "자신의 스킬 카드를 사용할 때, 10% 확률로 추가로 강한 빛을 발사하여 적에게 1회 피해를 주고 [기절]시킨다",
    "source": "해각시 - 철안국 현상금 임무\n흑월 상점\n운행 노선 자작나무 부표 드랍"
  },
  {
    "id": 104,
    "name": "\"극좌표\" 지휘 드론\n“极坐标”指挥无人机",
    "rarity": "SR",
    "type": "펜던드",
    "faction": "아니타",
    "stat_type": "생명력",
    "min_value": 3005,
    "max_value": 23738,
    "effect": "자신의 드론 특성이 있는 카드가 일으키는 피해 20% 증가한다.\n중첩 가능",
    "source": "7호 자유항 - 철도보안국 현상금 임무\r\n에너지 연구소  - 작전 계획\r\n흑월 상점\r\n운행 노선 자작나무 부표 드랍"
  },
  {
    "id": 105,
    "name": "크리안 사진기\n克里安照相机",
    "rarity": "SR",
    "type": "펜던드",
    "faction": "혼돈의 바다",
    "stat_type": "생명력",
    "min_value": 3053,
    "max_value": 24117,
    "effect": "[저주] 효과에 면역이 된다.",
    "source": "7호 자유항 - 철도보안국 현상금 임무\n에너지 연구소  - 작전 계획\n흑월 상점\n운행 노선 자작나무 부표 드랍"
  },
  {
    "id": 106,
    "name": "응급 처치 기기\n掐人中抢救器",
    "rarity": "SR",
    "type": "펜던드",
    "faction": "혼돈의 바다",
    "stat_type": "생명력",
    "min_value": 3149,
    "max_value": 24876,
    "effect": "받는 [기절] 및 [수면] 효과의 지속 시간이 1초 감소한다.\n중첩 가능",
    "source": "골든원더랜드 - 작전 계획\n흑월 상점\n운행 노선 자작나무 부표 드랍"
  },
  {
    "id": 107,
    "name": "사자 엠블럼\n狮子纹章",
    "rarity": "SR",
    "type": "펜던드",
    "faction": "제국",
    "stat_type": "생명력",
    "min_value": 2947,
    "max_value": 23283,
    "effect": "자신의 퍼플 카드가 일으키는 피해가 15% 증가한다.\n중첩 가능",
    "source": "흑월 상점\n운행 노선 자작나무 부표 드랍"
  },
  {
    "id": 108,
    "name": "창위의 약탈자\n“四翼妖龙”",
    "rarity": "SR",
    "type": "펜던드",
    "faction": "흑월",
    "stat_type": "생명력",
    "min_value": 3024,
    "max_value": 23890,
    "effect": "리더스킬 사용 시, 드론 지원을 획득한다.",
    "source": "곤루시 - 철안국 현상수배 임무\n흑월 상점\n운행 노선 자작나무 부표 드랍"
  },
  {
    "id": 109,
    "name": "동력식 회수 기계\n动能回收器",
    "rarity": "SR",
    "type": "펜던드",
    "faction": "철맹",
    "stat_type": "생명력",
    "min_value": 3014,
    "max_value": 23813,
    "effect": "적을 처치할 때마다, 0.4의 코스트를 획득한다.\n중첩 가능",
    "source": "슈그리 시 - 철도 보안국 현상금 임무\n멘더 광산 -  철 안전국 현상금 임무\n황원역 - 전투 계획\n흑월 상점\n운행 노선 자작나무 부표 드랍"
  },
  {
    "id": 110,
    "name": "히포크레네\n灵泉",
    "rarity": "SR",
    "type": "펜던드",
    "faction": "제국",
    "stat_type": "생명력",
    "min_value": 2893,
    "max_value": 22853,
    "effect": "매초 0.02의 코스트를 획득한다.\n중첩 가능",
    "source": "흑월 상점\n운행 노선 자작나무 부표 드랍"
  },
  {
    "id": 111,
    "name": "무의식 학습 장치\n无意识学习装置",
    "rarity": "SR",
    "type": "펜던트",
    "faction": "학회",
    "stat_type": "생명력",
    "min_value": 3178,
    "max_value": 25103,
    "effect": "폐기 명령의 재사용 대기시간 1초 감소한다.\n중첩 가능",
    "source": "해각시 - 철안국 현상금 임무\n흑월 상점\n운행 노선 자작나무 부표 드랍"
  },
  {
    "id": 112,
    "name": "로크웰 금속\n洛克维尔金属",
    "rarity": "R",
    "type": "갑옷",
    "faction": "혼돈의 바다",
    "stat_type": "방어력",
    "min_value": 24,
    "max_value": 191,
    "effect": "전투 시작 시, 자신의 방어력 5%이 증가한다.\n중첩 가능",
    "source": "골든원더랜드 - 작전 계획\n흑월 상점\n운행 노선 자작나무 부표 드랍"
  },
  {
    "id": 113,
    "name": "비금속 도금 재료\n非金属材料镀层",
    "rarity": "R",
    "type": "갑옷",
    "faction": "아니타",
    "stat_type": "방어력",
    "min_value": 24,
    "max_value": 192,
    "effect": "자신의 블루 카드를 사용할 때마다, 자신의 방어력이 0.5% 증가한다.\n중첩 가능",
    "source": "7호 자유항 - 철도보안국 현상금 임무\n에너지 연구소  - 작전 계획\n흑월 상점\n운행 노선 자작나무 부표 드랍"
  },
  {
    "id": 114,
    "name": "케블라 수트\n西装凯夫拉",
    "rarity": "R",
    "type": "갑옷",
    "faction": "흑월",
    "stat_type": "방어력",
    "min_value": 24,
    "max_value": 191,
    "effect": "자신의 [은신] 상태 해제 시, 자신의 생명력이 3% 회복된다.\n중첩 가능",
    "source": "곤루시 - 철안국 현상수배 임무\n흑월 상점\n운행 노선 자작나무 부표 드랍"
  },
  {
    "id": 115,
    "name": "기본 방어 섬유\n标准防御纤维",
    "rarity": "R",
    "type": "갑옷",
    "faction": "학회",
    "stat_type": "방어력",
    "min_value": 23,
    "max_value": 180,
    "effect": "5% 확률로 받은 공격을 막고, 이 피해를 무시한다.\n확률 중첩 가능",
    "source": "해각시 - 철안국 현상금 임무\n흑월 상점\n운행 노선 자작나무 부표 드랍"
  },
  {
    "id": 116,
    "name": "구급 아머\n急救护甲",
    "rarity": "R",
    "type": "갑옷",
    "faction": "철맹",
    "stat_type": "방어력",
    "min_value": 24,
    "max_value": 190,
    "effect": "자신의 생명력이 30% 미만일 때, 아드레날린 응급 처치 주사로 자신의 생명력을 10% 회복한다.",
    "source": "슈그리 시 - 철도 보안국 현상금 임무\n멘더 광산 -  철 안전국 현상금 임무\n황원역 - 전투 계획\n흑월 상점\n운행 노선 자작나무 부표 드랍"
  },
  {
    "id": 117,
    "name": "레드 브론즈 아머\n红铜护甲",
    "rarity": "R",
    "type": "갑옷",
    "faction": "제국",
    "stat_type": "방어력",
    "min_value": 24,
    "max_value": 187,
    "effect": "[암흑예술]로 입힌 피해의 10%를 자신의 생명력으로 회복한다.\n중첩 가능",
    "source": "흑월 상점\n운행 노선 자작나무 부표 드랍"
  },
  {
    "id": 118,
    "name": "A77 우주 비행 권총\nA77航天手枪",
    "rarity": "R",
    "type": "무기",
    "faction": "아니타",
    "stat_type": "공격력",
    "min_value": 24,
    "max_value": 192,
    "effect": "자신의 레드카드를 사용할 때마다, 자신의 일반 공격 속도가 5% 증가한다.\n최대 100%",
    "source": "7호 자유항 - 철도보안국 현상금 임무\n에너지 연구소  - 작전 계획\n흑월 상점\n운행 노선 자작나무 부표 드랍"
  },
  {
    "id": 119,
    "name": "어장 단검\n鱼肠短刀",
    "rarity": "R",
    "type": "무기",
    "faction": "흑월",
    "stat_type": "공격력",
    "min_value": 24,
    "max_value": 187,
    "effect": "자신이 일으키는 [열상] 피해가 15% 증가한다.\n중첩 가능",
    "source": "곤루시 - 철안국 현상수배 임무\n흑월 상점\n운행 노선 자작나무 부표 드랍"
  },
  {
    "id": 120,
    "name": "사냥용 리볼버\n狩猎左轮",
    "rarity": "R",
    "type": "무기",
    "faction": "철맹",
    "stat_type": "공격력",
    "min_value": 22,
    "max_value": 175,
    "effect": "적의 웨이브를 한 번 물리칠 때마다, 자신의 공격력이 3% 증가한다.\n중첩 가능",
    "source": "슈그리 시 - 철도 보안국 현상금 임무\n멘더 광산 -  철 안전국 현상금 임무\n황원역 - 전투 계획\n흑월 상점\n운행 노선 자작나무 부표 드랍"
  },
  {
    "id": 121,
    "name": "흑월 독화살\n黑月毒镖",
    "rarity": "R",
    "type": "무기",
    "faction": "흑월",
    "stat_type": "공격력",
    "min_value": 24,
    "max_value": 189,
    "effect": "자신이 일으키는 [화상] 피해가 15% 증가한다.\n중첩 가능",
    "source": "곤루시 - 철안국 현상수배 임무\n흑월 상점\n운행 노선 자작나무 부표 드랍"
  },
  {
    "id": 122,
    "name": "N-RAY 총\nN射线枪",
    "rarity": "R",
    "type": "무기",
    "faction": "혼돈의 바다",
    "stat_type": "공격력",
    "min_value": 23,
    "max_value": 182,
    "effect": "자신이 일으키는 [혼란] 지속 시간이 1초 증가한다.\n중첩 가능",
    "source": "골든원더랜드 - 작전 계획\n흑월 상점\n운행 노선 자작나무 부표 드랍"
  },
  {
    "id": 123,
    "name": "2호 장난감\n二号玩具",
    "rarity": "R",
    "type": "무기",
    "faction": "학회",
    "stat_type": "공격력",
    "min_value": 24,
    "max_value": 189,
    "effect": "리더스킬 사용 시, 자신의 방어력이 1.5% 증가한다.\n중첩 가능",
    "source": "해각시 - 철안국 현상금 임무\n흑월 상점\n황원역 - 레비스 교환\n운행 노선 자작나무 부표 드랍"
  },
  {
    "id": 124,
    "name": "마술봉\n引魔法杖",
    "rarity": "R",
    "type": "무기",
    "faction": "제국",
    "stat_type": "공격력",
    "min_value": 24,
    "max_value": 187,
    "effect": "퍼플 카드를 사용할 때, 20% 확률로 1의 코스트를 획득한다.\n확률 중첩 가능",
    "source": "흑월 상점\r\n운행 노선 자작나무 부표 드랍"
  },
  {
    "id": 125,
    "name": "인챈티드 단검\n附魔短剑",
    "rarity": "R",
    "type": "무기",
    "faction": "제국",
    "stat_type": "공격력",
    "min_value": 23,
    "max_value": 182,
    "effect": "퍼플 카드를 사용할 때, 10% 확률로 카드 한 장을 뽑는다.\n확률 중첩 가능",
    "source": "흑월 상점\n운행 노선 자작나무 부표 드랍"
  },
  {
    "id": 126,
    "name": "질량 투사기\n质量投射器",
    "rarity": "R",
    "type": "무기",
    "faction": "학회",
    "stat_type": "공격력",
    "min_value": 24,
    "max_value": 191,
    "effect": "리더스킬 사용 시, 자신의 공격력이 1.5% 증가한다.\n중첩 가능",
    "source": "해각시 - 철안국 현상금 임무\n흑월 상점\n황원역 - 레비스 교환\n운행 노선 자작나무 부표 드랍"
  },
  {
    "id": 127,
    "name": "사냥칼\n荒野猎刀",
    "rarity": "R",
    "type": "무기",
    "faction": "철맹",
    "stat_type": "공격력",
    "min_value": 24,
    "max_value": 192,
    "effect": "적의 웨이브를 한 번 물리칠 때마다, 자신의 방어력이 3% 증가한다.\n중첩 가능",
    "source": "슈그리 시 - 철도 보안국 현상금 임무\n멘더 광산 -  철 안전국 현상금 임무\n황원역 - 전투 계획\n흑월 상점\n운행 노선 자작나무 부표 드랍"
  },
  {
    "id": 128,
    "name": "다용도 오프너\n万用起子",
    "rarity": "R",
    "type": "무기",
    "faction": "아니타",
    "stat_type": "공격력",
    "min_value": 23,
    "max_value": 178,
    "effect": "자신의 레드 카드를 사용할 때마다, 자신의 공격력이 0.5% 증가한다.\n중첩 가능",
    "source": "7호 자유항 - 철도보안국 현상금 임무\n에너지 연구소  - 작전 계획\n흑월 상점\n운행 노선 자작나무 부표 드랍"
  },
  {
    "id": 129,
    "name": "흑월 연막탄\n黑月烟雾弹",
    "rarity": "R",
    "type": "펜던드",
    "faction": "흑월",
    "stat_type": "생명력",
    "min_value": 2413,
    "max_value": 19064,
    "effect": "전투 시작 시 2초 동안 은신한다.\n중첩 가능",
    "source": "곤루시 - 철안국 현상수배 임무\r\n흑월 상점\r\n운행 노선 자작나무 부표 드랍"
  },
  {
    "id": 130,
    "name": "고양이 엠블럼\n猫纹章",
    "rarity": "R",
    "type": "펜던드",
    "faction": "제국",
    "stat_type": "생명력",
    "min_value": 2315,
    "max_value": 18290,
    "effect": "자신이 유발한 [변신] 지속 시간 1초 증가한다.\n중첩 가능",
    "source": "흑월 상점\r\n운행 노선 자작나무 부표 드랍"
  },
  {
    "id": 131,
    "name": "철가마\n接功铁锅",
    "rarity": "R",
    "type": "펜던드",
    "faction": "혼돈의 바다",
    "stat_type": "생명력",
    "min_value": 2281,
    "max_value": 18020,
    "effect": "전투 시작 시 자신의 공격력이 5% 증가한다.\n중첩 가능",
    "source": "골든원더랜드 - 작전 계획\n흑월 상점\n운행 노선 자작나무 부표 드랍"
  },
  {
    "id": 132,
    "name": "파편 커버\n破片套",
    "rarity": "R",
    "type": "펜던드",
    "faction": "철맹",
    "stat_type": "생명력",
    "min_value": 2347,
    "max_value": 18542,
    "effect": "자신의 폭발물로 입히는 피해가 10% 증가한다.\n중첩 가능",
    "source": "슈그리 시 - 철도 보안국 현상금 임무\n멘더 광산 -  철 안전국 현상금 임무\n황원역 - 전투 계획\n흑월 상점\n운행 노선 자작나무 부표 드랍"
  },
  {
    "id": 133,
    "name": "해리슨 장치\n哈里森装置",
    "rarity": "R",
    "type": "펜던드",
    "faction": "혼돈의 바다",
    "stat_type": "생명력",
    "min_value": 2411,
    "max_value": 19046,
    "effect": "옐로 카드를 사용할 때마다 0.3코스트 비용을 획득한다.\n중첩 불가",
    "source": "골든원더랜드 - 작전 계획\n흑월 상점\n운행 노선 자작나무 부표 드랍"
  },
  {
    "id": 134,
    "name": "기능성 음료수\n特浓功能饮料",
    "rarity": "R",
    "type": "펜던드",
    "faction": "철맹",
    "stat_type": "생명력",
    "min_value": 2264,
    "max_value": 17884,
    "effect": "적의 한 웨이브를 물리칠 때마다 1코스트 비용을 획득한다.\n중첩 가능",
    "source": "슈그리 시 - 철도 보안국 현상금 임무\r\n멘더 광산 -  철 안전국 현상금 임무\r\n황원역 - 전투 계획\r\n흑월 상점\r\n운행 노선 자작나무 부표 드랍"
  },
  {
    "id": 135,
    "name": "고열량 식량\n高热量军粮",
    "rarity": "R",
    "type": "펜던드",
    "faction": "철맹",
    "stat_type": "생명력",
    "min_value": 2394,
    "max_value": 18910,
    "effect": "적의 한 웨이브를 물리칠 때마다 자신의 생명력을 10% 회복한다.\n중첩 가능",
    "source": "슈그리 시 - 철도 보안국 현상금 임무\r\n멘더 광산 -  철 안전국 현상금 임무\r\n황원역 - 전투 계획\r\n흑월 상점\r\n운행 노선 자작나무 부표 드랍"
  },
  {
    "id": 136,
    "name": "제세동기\n便携除颤器",
    "rarity": "R",
    "type": "펜던드",
    "faction": "아니타",
    "stat_type": "생명력",
    "min_value": 2355,
    "max_value": 18601,
    "effect": "자신의 [인뢰], [낙뢰], [우레], [천둥]의 피해가 15% 증가한다.\n중첩 가능",
    "source": "7호 자유항 - 철도보안국 현상금 임무\r\n에너지 연구소  - 작전 계획\r\n흑월 상점\r\n운행 노선 자작나무 부표 드랍"
  },
  {
    "id": 137,
    "name": "포일 모자\n锡纸帽",
    "rarity": "R",
    "type": "펜던드",
    "faction": "혼돈의 바다",
    "stat_type": "생명력",
    "min_value": 2337,
    "max_value": 18464,
    "effect": "혼란 효과에 면역이 된다.",
    "source": "골든원더랜드 - 작전 계획\r\n흑월 상점\r\n운행 노선 자작나무 부표 드랍"
  },
  {
    "id": 138,
    "name": "원기 회복 기기\n提神醒脑仪",
    "rarity": "R",
    "type": "펜던트",
    "faction": "학회",
    "stat_type": "생명력",
    "min_value": 2404,
    "max_value": 18988,
    "effect": "자신의 모든 확률 기반 메커니즘의 확률이 3% 증가한다.\n중첩 가능",
    "source": "해각시 - 철안국 현상금 임무\r\n흑월 상점\r\n운행 노선 자작나무 부표 드랍"
  }
]